aioiliad/IliadData.py
aioiliad/__init__.py
aioiliad/xpaths.py
aioiliad-0.3.1.dist-info/DESCRIPTION.rst
aioiliad-0.3.1.dist-info/METADATA
aioiliad-0.3.1.dist-info/RECORD
aioiliad-0.3.1.dist-info/WHEEL
aioiliad-0.3.1.dist-info/metadata.json
aioiliad-0.3.1.dist-info/top_level.txt
